{
	"count": 20,
	"start": 0,
	"total": 26,
	"subjects": [{
		"rating": {
			"max": 10,
			"average": 6.5,
			"stars": "35",
			"min": 0
		},
		"genres": ["\u52a8\u4f5c", "\u79d1\u5e7b", "\u72af\u7f6a"],
		"title": "\u653b\u58f3\u673a\u52a8\u961f",
		"casts": [{
			"alt": "https:\/\/movie.douban.com\/celebrity\/1054453\/",
			"avatars": {
				"small": "https://img3.doubanio.com\/img\/celebrity\/small\/37050.jpg",
				"large": "https://img3.doubanio.com\/img\/celebrity\/large\/37050.jpg",
				"medium": "https://img3.doubanio.com\/img\/celebrity\/medium\/37050.jpg"
			},
			"name": "\u65af\u5609\u4e3d\u00b7\u7ea6\u7ff0\u900a",
			"id": "1054453"
		}, {
			"alt": "https:\/\/movie.douban.com\/celebrity\/1032805\/",
			"avatars": {
				"small": "https://img1.doubanio.com\/img\/celebrity\/small\/1366032638.59.jpg",
				"large": "https://img1.doubanio.com\/img\/celebrity\/large\/1366032638.59.jpg",
				"medium": "https://img1.doubanio.com\/img\/celebrity\/medium\/1366032638.59.jpg"
			},
			"name": "\u76ae\u9c81\u00b7\u57c3\u65af\u8d1d\u514b",
			"id": "1032805"
		}, {
			"alt": "https:\/\/movie.douban.com\/celebrity\/1054423\/",
			"avatars": {
				"small": "https://img3.doubanio.com\/img\/celebrity\/small\/39452.jpg",
				"large": "https://img3.doubanio.com\/img\/celebrity\/large\/39452.jpg",
				"medium": "https://img3.doubanio.com\/img\/celebrity\/medium\/39452.jpg"
			},
			"name": "\u5317\u91ce\u6b66",
			"id": "1054423"
		}],
		"collect_count": 21430,
		"original_title": "Ghost in the Shell",
		"subtype": "movie",
		"directors": [{
			"alt": "https:\/\/movie.douban.com\/celebrity\/1320096\/",
			"avatars": {
				"small": "https://img3.doubanio.com\/img\/celebrity\/small\/52315.jpg",
				"large": "https://img3.doubanio.com\/img\/celebrity\/large\/52315.jpg",
				"medium": "https://img3.doubanio.com\/img\/celebrity\/medium\/52315.jpg"
			},
			"name": "\u9c81\u4f2f\u7279\u00b7\u6851\u5fb7\u65af",
			"id": "1320096"
		}],
		"year": "2017",
		"images": {
			"small": "https://img3.doubanio.com\/view\/movie_poster_cover\/ipst\/public\/p2453176400.webp",
			"large": "https://img3.doubanio.com\/view\/movie_poster_cover\/lpst\/public\/p2453176400.webp",
			"medium": "https://img3.doubanio.com\/view\/movie_poster_cover\/spst\/public\/p2453176400.webp"
		},
		"alt": "https:\/\/movie.douban.com\/subject\/25818101\/",
		"id": "25818101"
	}, {
		"rating": {
			"max": 10,
			"average": 6.8,
			"stars": "35",
			"min": 0
		},
		"genres": ["\u52a8\u4f5c", "\u5947\u5e7b", "\u5192\u9669"],
		"title": "\u91d1\u521a\uff1a\u9ab7\u9ac5\u5c9b",
		"casts": [{
			"alt": "https:\/\/movie.douban.com\/celebrity\/1004596\/",
			"avatars": {
				"small": "https://img3.doubanio.com\/img\/celebrity\/small\/35625.jpg",
				"large": "https://img3.doubanio.com\/img\/celebrity\/large\/35625.jpg",
				"medium": "https://img3.doubanio.com\/img\/celebrity\/medium\/35625.jpg"
			},
			"name": "\u6c64\u59c6\u00b7\u5e0c\u5fb7\u52d2\u65af\u987f",
			"id": "1004596"
		}, {
			"alt": "https:\/\/movie.douban.com\/celebrity\/1027194\/",
			"avatars": {
				"small": "https://img3.doubanio.com\/img\/celebrity\/small\/1392029372.12.jpg",
				"large": "https://img3.doubanio.com\/img\/celebrity\/large\/1392029372.12.jpg",
				"medium": "https://img3.doubanio.com\/img\/celebrity\/medium\/1392029372.12.jpg"
			},
			"name": "\u5e03\u4e3d\u00b7\u62c9\u5c14\u68ee",
			"id": "1027194"
		}, {
			"alt": "https:\/\/movie.douban.com\/celebrity\/1054408\/",
			"avatars": {
				"small": "https://img3.doubanio.com\/img\/celebrity\/small\/31870.jpg",
				"large": "https://img3.doubanio.com\/img\/celebrity\/large\/31870.jpg",
				"medium": "https://img3.doubanio.com\/img\/celebrity\/medium\/31870.jpg"
			},
			"name": "\u585e\u7f2a\u5c14\u00b7\u6770\u514b\u900a",
			"id": "1054408"
		}],
		"collect_count": 81224,
		"original_title": "Kong: Skull Island",
		"subtype": "movie",
		"directors": [{
			"alt": "https:\/\/movie.douban.com\/celebrity\/1326532\/",
			"avatars": {
				"small": "https://img1.doubanio.com\/img\/celebrity\/small\/1359526353.7.jpg",
				"large": "https://img1.doubanio.com\/img\/celebrity\/large\/1359526353.7.jpg",
				"medium": "https://img1.doubanio.com\/img\/celebrity\/medium\/1359526353.7.jpg"
			},
			"name": "\u4e54\u4e39\u00b7\u6c83\u683c\u7279-\u7f57\u4f2f\u8328",
			"id": "1326532"
		}],
		"year": "2017",
		"images": {
			"small": "https://img1.doubanio.com\/view\/movie_poster_cover\/ipst\/public\/p2436030518.webp",
			"large": "https://img1.doubanio.com\/view\/movie_poster_cover\/lpst\/public\/p2436030518.webp",
			"medium": "https://img1.doubanio.com\/view\/movie_poster_cover\/spst\/public\/p2436030518.webp"
		},
		"alt": "https:\/\/movie.douban.com\/subject\/26309788\/",
		"id": "26309788"
	}, {
		"rating": {
			"max": 10,
			"average": 6.6,
			"stars": "35",
			"min": 0
		},
		"genres": ["\u72af\u7f6a", "\u60ac\u7591"],
		"title": "\u5acc\u7591\u4ebaX\u7684\u732e\u8eab",
		"casts": [{
			"alt": "https:\/\/movie.douban.com\/celebrity\/1314544\/",
			"avatars": {
				"small": "https://img3.doubanio.com\/img\/celebrity\/small\/1444998211.72.jpg",
				"large": "https://img3.doubanio.com\/img\/celebrity\/large\/1444998211.72.jpg",
				"medium": "https://img3.doubanio.com\/img\/celebrity\/medium\/1444998211.72.jpg"
			},
			"name": "\u738b\u51ef",
			"id": "1314544"
		}, {
			"alt": "https:\/\/movie.douban.com\/celebrity\/1323723\/",
			"avatars": {
				"small": "https://img3.doubanio.com\/img\/celebrity\/small\/1416748988.73.jpg",
				"large": "https://img3.doubanio.com\/img\/celebrity\/large\/1416748988.73.jpg",
				"medium": "https://img3.doubanio.com\/img\/celebrity\/medium\/1416748988.73.jpg"
			},
			"name": "\u5f20\u9c81\u4e00",
			"id": "1323723"
		}, {
			"alt": "https:\/\/movie.douban.com\/celebrity\/1005214\/",
			"avatars": {
				"small": "https://img3.doubanio.com\/img\/celebrity\/small\/36663.jpg",
				"large": "https://img3.doubanio.com\/img\/celebrity\/large\/36663.jpg",
				"medium": "https://img3.doubanio.com\/img\/celebrity\/medium\/36663.jpg"
			},
			"name": "\u6797\u5fc3\u5982",
			"id": "1005214"
		}],
		"collect_count": 71619,
		"original_title": "\u5acc\u7591\u4ebaX\u7684\u732e\u8eab",
		"subtype": "movie",
		"directors": [{
			"alt": "https:\/\/movie.douban.com\/celebrity\/1050540\/",
			"avatars": {
				"small": "https://img3.doubanio.com\/img\/celebrity\/small\/27354.jpg",
				"large": "https://img3.doubanio.com\/img\/celebrity\/large\/27354.jpg",
				"medium": "https://img3.doubanio.com\/img\/celebrity\/medium\/27354.jpg"
			},
			"name": "\u82cf\u6709\u670b",
			"id": "1050540"
		}],
		"year": "2017",
		"images": {
			"small": "https://img3.doubanio.com\/view\/movie_poster_cover\/ipst\/public\/p2448676053.webp",
			"large": "https://img3.doubanio.com\/view\/movie_poster_cover\/lpst\/public\/p2448676053.webp",
			"medium": "https://img3.doubanio.com\/view\/movie_poster_cover\/spst\/public\/p2448676053.webp"
		},
		"alt": "https:\/\/movie.douban.com\/subject\/26606743\/",
		"id": "26606743"
	}, {
		"rating": {
			"max": 10,
			"average": 6.6,
			"stars": "35",
			"min": 0
		},
		"genres": ["\u5267\u60c5", "\u52a8\u4f5c", "\u72af\u7f6a"],
		"title": "\u975e\u51e1\u4efb\u52a1",
		"casts": [{
			"alt": "https:\/\/movie.douban.com\/celebrity\/1276105\/",
			"avatars": {
				"small": "https://img3.doubanio.com\/img\/celebrity\/small\/1403053084.22.jpg",
				"large": "https://img3.doubanio.com\/img\/celebrity\/large\/1403053084.22.jpg",
				"medium": "https://img3.doubanio.com\/img\/celebrity\/medium\/1403053084.22.jpg"
			},
			"name": "\u9ec4\u8f69",
			"id": "1276105"
		}, {
			"alt": "https:\/\/movie.douban.com\/celebrity\/1274291\/",
			"avatars": {
				"small": "https://img1.doubanio.com\/img\/celebrity\/small\/8898.jpg",
				"large": "https://img1.doubanio.com\/img\/celebrity\/large\/8898.jpg",
				"medium": "https://img1.doubanio.com\/img\/celebrity\/medium\/8898.jpg"
			},
			"name": "\u6bb5\u5955\u5b8f",
			"id": "1274291"
		}, {
			"alt": "https:\/\/movie.douban.com\/celebrity\/1330484\/",
			"avatars": {
				"small": "https://img1.doubanio.com\/img\/celebrity\/small\/1372053646.57.jpg",
				"large": "https://img1.doubanio.com\/img\/celebrity\/large\/1372053646.57.jpg",
				"medium": "https://img1.doubanio.com\/img\/celebrity\/medium\/1372053646.57.jpg"
			},
			"name": "\u90ce\u6708\u5a77",
			"id": "1330484"
		}],
		"collect_count": 19630,
		"original_title": "\u975e\u51e1\u4efb\u52a1",
		"subtype": "movie",
		"directors": [{
			"alt": "https:\/\/movie.douban.com\/celebrity\/1126158\/",
			"avatars": {
				"small": "https://img1.doubanio.com\/img\/celebrity\/small\/3547.jpg",
				"large": "https://img1.doubanio.com\/img\/celebrity\/large\/3547.jpg",
				"medium": "https://img1.doubanio.com\/img\/celebrity\/medium\/3547.jpg"
			},
			"name": "\u9ea6\u5146\u8f89",
			"id": "1126158"
		}, {
			"alt": "https:\/\/movie.douban.com\/celebrity\/1307639\/",
			"avatars": {
				"small": "https://img3.doubanio.com\/img\/celebrity\/small\/19591.jpg",
				"large": "https://img3.doubanio.com\/img\/celebrity\/large\/19591.jpg",
				"medium": "https://img3.doubanio.com\/img\/celebrity\/medium\/19591.jpg"
			},
			"name": "\u6f58\u8000\u660e",
			"id": "1307639"
		}],
		"year": "2017",
		"images": {
			"small": "https://img1.doubanio.com\/view\/movie_poster_cover\/ipst\/public\/p2453197648.webp",
			"large": "https://img1.doubanio.com\/view\/movie_poster_cover\/lpst\/public\/p2453197648.webp",
			"medium": "https://img1.doubanio.com\/view\/movie_poster_cover\/spst\/public\/p2453197648.webp"
		},
		"alt": "https:\/\/movie.douban.com\/subject\/26616690\/",
		"id": "26616690"
	}, {
		"rating": {
			"max": 10,
			"average": 7.4,
			"stars": "40",
			"min": 0
		},
		"genres": ["\u7231\u60c5", "\u5947\u5e7b", "\u6b4c\u821e"],
		"title": "\u7f8e\u5973\u4e0e\u91ce\u517d",
		"casts": [{
			"alt": "https:\/\/movie.douban.com\/celebrity\/1053624\/",
			"avatars": {
				"small": "https://img3.doubanio.com\/img\/celebrity\/small\/10321.jpg",
				"large": "https://img3.doubanio.com\/img\/celebrity\/large\/10321.jpg",
				"medium": "https://img3.doubanio.com\/img\/celebrity\/medium\/10321.jpg"
			},
			"name": "\u827e\u739b\u00b7\u6c83\u68ee",
			"id": "1053624"
		}, {
			"alt": "https:\/\/movie.douban.com\/celebrity\/1027527\/",
			"avatars": {
				"small": "https://img3.doubanio.com\/img\/celebrity\/small\/1359042267.71.jpg",
				"large": "https://img3.doubanio.com\/img\/celebrity\/large\/1359042267.71.jpg",
				"medium": "https://img3.doubanio.com\/img\/celebrity\/medium\/1359042267.71.jpg"
			},
			"name": "\u4e39\u00b7\u53f2\u8482\u6587\u65af",
			"id": "1027527"
		}, {
			"alt": "https:\/\/movie.douban.com\/celebrity\/1276136\/",
			"avatars": {
				"small": "https://img3.doubanio.com\/img\/celebrity\/small\/36425.jpg",
				"large": "https://img3.doubanio.com\/img\/celebrity\/large\/36425.jpg",
				"medium": "https://img3.doubanio.com\/img\/celebrity\/medium\/36425.jpg"
			},
			"name": "\u5362\u514b\u00b7\u4f0a\u4e07\u65af",
			"id": "1276136"
		}],
		"collect_count": 111063,
		"original_title": "Beauty and the Beast",
		"subtype": "movie",
		"directors": [{
			"alt": "https:\/\/movie.douban.com\/celebrity\/1027245\/",
			"avatars": {
				"small": "https://img3.doubanio.com\/img\/celebrity\/small\/42170.jpg",
				"large": "https://img3.doubanio.com\/img\/celebrity\/large\/42170.jpg",
				"medium": "https://img3.doubanio.com\/img\/celebrity\/medium\/42170.jpg"
			},
			"name": "\u6bd4\u5c14\u00b7\u5eb7\u987f",
			"id": "1027245"
		}],
		"year": "2017",
		"images": {
			"small": "https://img3.doubanio.com\/view\/movie_poster_cover\/ipst\/public\/p2417948644.webp",
			"large": "https://img3.doubanio.com\/view\/movie_poster_cover\/lpst\/public\/p2417948644.webp",
			"medium": "https://img3.doubanio.com\/view\/movie_poster_cover\/spst\/public\/p2417948644.webp"
		},
		"alt": "https:\/\/movie.douban.com\/subject\/25900945\/",
		"id": "25900945"
	}, {
		"rating": {
			"max": 10,
			"average": 5.3,
			"stars": "30",
			"min": 0
		},
		"genres": ["\u52a8\u4f5c", "\u72af\u7f6a"],
		"title": "\u7ed1\u67b6\u8005",
		"casts": [{
			"alt": "https:\/\/movie.douban.com\/celebrity\/1275542\/",
			"avatars": {
				"small": "https://img1.doubanio.com\/img\/celebrity\/small\/21559.jpg",
				"large": "https://img1.doubanio.com\/img\/celebrity\/large\/21559.jpg",
				"medium": "https://img1.doubanio.com\/img\/celebrity\/medium\/21559.jpg"
			},
			"name": "\u767d\u767e\u4f55",
			"id": "1275542"
		}, {
			"alt": "https:\/\/movie.douban.com\/celebrity\/1275466\/",
			"avatars": {
				"small": "https://img3.doubanio.com\/img\/celebrity\/small\/12953.jpg",
				"large": "https://img3.doubanio.com\/img\/celebrity\/large\/12953.jpg",
				"medium": "https://img3.doubanio.com\/img\/celebrity\/medium\/12953.jpg"
			},
			"name": "\u9ec4\u7acb\u884c",
			"id": "1275466"
		}, {
			"alt": "https:\/\/movie.douban.com\/celebrity\/1312782\/",
			"avatars": {
				"small": "https://img3.doubanio.com\/img\/celebrity\/small\/1365319007.73.jpg",
				"large": "https://img3.doubanio.com\/img\/celebrity\/large\/1365319007.73.jpg",
				"medium": "https://img3.doubanio.com\/img\/celebrity\/medium\/1365319007.73.jpg"
			},
			"name": "\u660e\u9053",
			"id": "1312782"
		}],
		"collect_count": 10375,
		"original_title": "\u7ed1\u67b6\u8005",
		"subtype": "movie",
		"directors": [{
			"alt": "https:\/\/movie.douban.com\/celebrity\/1000571\/",
			"avatars": {
				"small": "https://img1.doubanio.com\/img\/celebrity\/small\/20738.jpg",
				"large": "https://img1.doubanio.com\/img\/celebrity\/large\/20738.jpg",
				"medium": "https://img1.doubanio.com\/img\/celebrity\/medium\/20738.jpg"
			},
			"name": "\u5f90\u9759\u857e",
			"id": "1000571"
		}],
		"year": "2017",
		"images": {
			"small": "https://img3.doubanio.com\/view\/movie_poster_cover\/ipst\/public\/p2445601403.webp",
			"large": "https://img3.doubanio.com\/view\/movie_poster_cover\/lpst\/public\/p2445601403.webp",
			"medium": "https://img3.doubanio.com\/view\/movie_poster_cover\/spst\/public\/p2445601403.webp"
		},
		"alt": "https:\/\/movie.douban.com\/subject\/26602933\/",
		"id": "26602933"
	}, {
		"rating": {
			"max": 10,
			"average": 6,
			"stars": "30",
			"min": 0
		},
		"genres": ["\u559c\u5267", "\u52a8\u753b", "\u5bb6\u5ead"],
		"title": "\u51b0\u96ea\u5927\u4f5c\u6218",
		"casts": [{
			"alt": "https:\/\/movie.douban.com\/celebrity\/1367823\/",
			"avatars": {
				"small": "https://img1.doubanio.com\/f\/movie\/ca527386eb8c4e325611e22dfcb04cc116d6b423\/pics\/movie\/celebrity-default-small.png",
				"large": "https://img3.doubanio.com\/f\/movie\/63acc16ca6309ef191f0378faf793d1096a3e606\/pics\/movie\/celebrity-default-large.png",
				"medium": "https://img1.doubanio.com\/f\/movie\/8dd0c794499fe925ae2ae89ee30cd225750457b4\/pics\/movie\/celebrity-default-medium.png"
			},
			"name": "\u5b89\u5409\u62c9\u00b7\u5609\u9c81\u76ae",
			"id": "1367823"
		}, {
			"alt": "https:\/\/movie.douban.com\/celebrity\/1014499\/",
			"avatars": {
				"small": "https://img3.doubanio.com\/img\/celebrity\/small\/4872.jpg",
				"large": "https://img3.doubanio.com\/img\/celebrity\/large\/4872.jpg",
				"medium": "https://img3.doubanio.com\/img\/celebrity\/medium\/4872.jpg"
			},
			"name": "\u739b\u4e3d\u6b27\u00b7\u6c83\u5c14\u592b",
			"id": "1014499"
		}, {
			"alt": "https:\/\/movie.douban.com\/celebrity\/1367824\/",
			"avatars": {
				"small": "https://img1.doubanio.com\/f\/movie\/ca527386eb8c4e325611e22dfcb04cc116d6b423\/pics\/movie\/celebrity-default-small.png",
				"large": "https://img3.doubanio.com\/f\/movie\/63acc16ca6309ef191f0378faf793d1096a3e606\/pics\/movie\/celebrity-default-large.png",
				"medium": "https://img1.doubanio.com\/f\/movie\/8dd0c794499fe925ae2ae89ee30cd225750457b4\/pics\/movie\/celebrity-default-medium.png"
			},
			"name": "\u9732\u8f9b\u8fbe\u00b7\u6234\u7ef4\u65af",
			"id": "1367824"
		}],
		"collect_count": 917,
		"original_title": "Snowtime!",
		"subtype": "movie",
		"directors": [{
			"alt": "https:\/\/movie.douban.com\/celebrity\/1294799\/",
			"avatars": {
				"small": "https://img1.doubanio.com\/f\/movie\/ca527386eb8c4e325611e22dfcb04cc116d6b423\/pics\/movie\/celebrity-default-small.png",
				"large": "https://img3.doubanio.com\/f\/movie\/63acc16ca6309ef191f0378faf793d1096a3e606\/pics\/movie\/celebrity-default-large.png",
				"medium": "https://img1.doubanio.com\/f\/movie\/8dd0c794499fe925ae2ae89ee30cd225750457b4\/pics\/movie\/celebrity-default-medium.png"
			},
			"name": "\u8ba9-\u5f17\u6717\u7d22\u74e6\u00b7\u6ce2\u7565\u7279",
			"id": "1294799"
		}, {
			"alt": "https:\/\/movie.douban.com\/celebrity\/1367821\/",
			"avatars": {
				"small": "https://img1.doubanio.com\/f\/movie\/ca527386eb8c4e325611e22dfcb04cc116d6b423\/pics\/movie\/celebrity-default-small.png",
				"large": "https://img3.doubanio.com\/f\/movie\/63acc16ca6309ef191f0378faf793d1096a3e606\/pics\/movie\/celebrity-default-large.png",
				"medium": "https://img1.doubanio.com\/f\/movie\/8dd0c794499fe925ae2ae89ee30cd225750457b4\/pics\/movie\/celebrity-default-medium.png"
			},
			"name": "\u5f17\u5170\u514b\u00b7\u5e03\u91cc\u68ee",
			"id": "1367821"
		}],
		"year": "2015",
		"images": {
			"small": "https://img3.doubanio.com\/view\/movie_poster_cover\/ipst\/public\/p2443765210.webp",
			"large": "https://img3.doubanio.com\/view\/movie_poster_cover\/lpst\/public\/p2443765210.webp",
			"medium": "https://img3.doubanio.com\/view\/movie_poster_cover\/spst\/public\/p2443765210.webp"
		},
		"alt": "https:\/\/movie.douban.com\/subject\/26681656\/",
		"id": "26681656"
	}, {
		"rating": {
			"max": 10,
			"average": 7.7,
			"stars": "40",
			"min": 0
		},
		"genres": ["\u5267\u60c5"],
		"title": "\u4e00\u5ff5\u65e0\u660e",
		"casts": [{
			"alt": "https:\/\/movie.douban.com\/celebrity\/1002862\/",
			"avatars": {
				"small": "https://img3.doubanio.com\/img\/celebrity\/small\/1161.jpg",
				"large": "https://img3.doubanio.com\/img\/celebrity\/large\/1161.jpg",
				"medium": "https://img3.doubanio.com\/img\/celebrity\/medium\/1161.jpg"
			},
			"name": "\u66fe\u5fd7\u4f1f",
			"id": "1002862"
		}, {
			"alt": "https:\/\/movie.douban.com\/celebrity\/1041510\/",
			"avatars": {
				"small": "https://img3.doubanio.com\/img\/celebrity\/small\/802.jpg",
				"large": "https://img3.doubanio.com\/img\/celebrity\/large\/802.jpg",
				"medium": "https://img3.doubanio.com\/img\/celebrity\/medium\/802.jpg"
			},
			"name": "\u4f59\u6587\u4e50",
			"id": "1041510"
		}, {
			"alt": "https:\/\/movie.douban.com\/celebrity\/1319116\/",
			"avatars": {
				"small": "https://img3.doubanio.com\/img\/celebrity\/small\/50861.jpg",
				"large": "https://img3.doubanio.com\/img\/celebrity\/large\/50861.jpg",
				"medium": "https://img3.doubanio.com\/img\/celebrity\/medium\/50861.jpg"
			},
			"name": "\u65b9\u7693\u739f",
			"id": "1319116"
		}],
		"collect_count": 2838,
		"original_title": "\u4e00\u5ff5\u7121\u660e",
		"subtype": "movie",
		"directors": [{
			"alt": "https:\/\/movie.douban.com\/celebrity\/1324490\/",
			"avatars": {
				"small": "https://img1.doubanio.com\/img\/celebrity\/small\/59259.jpg",
				"large": "https://img1.doubanio.com\/img\/celebrity\/large\/59259.jpg",
				"medium": "https://img1.doubanio.com\/img\/celebrity\/medium\/59259.jpg"
			},
			"name": "\u9ec4\u8fdb",
			"id": "1324490"
		}],
		"year": "2016",
		"images": {
			"small": "https://img3.doubanio.com\/view\/movie_poster_cover\/ipst\/public\/p2452970761.webp",
			"large": "https://img3.doubanio.com\/view\/movie_poster_cover\/lpst\/public\/p2452970761.webp",
			"medium": "https://img3.doubanio.com\/view\/movie_poster_cover\/spst\/public\/p2452970761.webp"
		},
		"alt": "https:\/\/movie.douban.com\/subject\/26704590\/",
		"id": "26704590"
	}, {
		"rating": {
			"max": 10,
			"average": 7.7,
			"stars": "40",
			"min": 0
		},
		"genres": ["\u5267\u60c5", "\u559c\u5267", "\u5bb6\u5ead"],
		"title": "\u4e00\u6761\u72d7\u7684\u4f7f\u547d",
		"casts": [{
			"alt": "https:\/\/movie.douban.com\/celebrity\/1000088\/",
			"avatars": {
				"small": "https://img3.doubanio.com\/img\/celebrity\/small\/1433487849.12.jpg",
				"large": "https://img3.doubanio.com\/img\/celebrity\/large\/1433487849.12.jpg",
				"medium": "https://img3.doubanio.com\/img\/celebrity\/medium\/1433487849.12.jpg"
			},
			"name": "\u5e03\u4e3d\u7279\u00b7\u7f57\u4f2f\u68ee",
			"id": "1000088"
		}, {
			"alt": "https:\/\/movie.douban.com\/celebrity\/1002679\/",
			"avatars": {
				"small": "https://img3.doubanio.com\/img\/celebrity\/small\/52.jpg",
				"large": "https://img3.doubanio.com\/img\/celebrity\/large\/52.jpg",
				"medium": "https://img3.doubanio.com\/img\/celebrity\/medium\/52.jpg"
			},
			"name": "\u4e39\u5c3c\u65af\u00b7\u594e\u5fb7",
			"id": "1002679"
		}, {
			"alt": "https:\/\/movie.douban.com\/celebrity\/1049592\/",
			"avatars": {
				"small": "https://img1.doubanio.com\/img\/celebrity\/small\/1376584681.68.jpg",
				"large": "https://img1.doubanio.com\/img\/celebrity\/large\/1376584681.68.jpg",
				"medium": "https://img1.doubanio.com\/img\/celebrity\/medium\/1376584681.68.jpg"
			},
			"name": "\u4f69\u5409\u00b7\u5229\u666e\u987f",
			"id": "1049592"
		}],
		"collect_count": 89479,
		"original_title": "A Dog's Purpose",
		"subtype": "movie",
		"directors": [{
			"alt": "https:\/\/movie.douban.com\/celebrity\/1018014\/",
			"avatars": {
				"small": "https://img3.doubanio.com\/img\/celebrity\/small\/4333.jpg",
				"large": "https://img3.doubanio.com\/img\/celebrity\/large\/4333.jpg",
				"medium": "https://img3.doubanio.com\/img\/celebrity\/medium\/4333.jpg"
			},
			"name": "\u62c9\u65af\u00b7\u970d\u5c14\u65af\u9053\u59c6",
			"id": "1018014"
		}],
		"year": "2017",
		"images": {
			"small": "https://img1.doubanio.com\/view\/movie_poster_cover\/ipst\/public\/p2432493858.webp",
			"large": "https://img1.doubanio.com\/view\/movie_poster_cover\/lpst\/public\/p2432493858.webp",
			"medium": "https://img1.doubanio.com\/view\/movie_poster_cover\/spst\/public\/p2432493858.webp"
		},
		"alt": "https:\/\/movie.douban.com\/subject\/6873143\/",
		"id": "6873143"
	}, {
		"rating": {
			"max": 10,
			"average": 5.6,
			"stars": "30",
			"min": 0
		},
		"genres": ["\u5267\u60c5", "\u559c\u5267"],
		"title": "\u6709\u5b8c\u6ca1\u5b8c",
		"casts": [{
			"alt": "https:\/\/movie.douban.com\/celebrity\/1051526\/",
			"avatars": {
				"small": "https://img1.doubanio.com\/img\/celebrity\/small\/1480174773.98.jpg",
				"large": "https://img1.doubanio.com\/img\/celebrity\/large\/1480174773.98.jpg",
				"medium": "https://img1.doubanio.com\/img\/celebrity\/medium\/1480174773.98.jpg"
			},
			"name": "\u8303\u4f1f",
			"id": "1051526"
		}, {
			"alt": "https:\/\/movie.douban.com\/celebrity\/1029332\/",
			"avatars": {
				"small": "https://img3.doubanio.com\/img\/celebrity\/small\/1432231412.3.jpg",
				"large": "https://img3.doubanio.com\/img\/celebrity\/large\/1432231412.3.jpg",
				"medium": "https://img3.doubanio.com\/img\/celebrity\/medium\/1432231412.3.jpg"
			},
			"name": "\u8d3e\u9759\u96ef",
			"id": "1029332"
		}, {
			"alt": "https:\/\/movie.douban.com\/celebrity\/1361735\/",
			"avatars": {
				"small": "https://img3.doubanio.com\/img\/celebrity\/small\/1481115129.43.jpg",
				"large": "https://img3.doubanio.com\/img\/celebrity\/large\/1481115129.43.jpg",
				"medium": "https://img3.doubanio.com\/img\/celebrity\/medium\/1481115129.43.jpg"
			},
			"name": "\u5218\u4fca\u660a",
			"id": "1361735"
		}],
		"collect_count": 2325,
		"original_title": "\u6709\u5b8c\u6ca1\u5b8c",
		"subtype": "movie",
		"directors": [{
			"alt": "https:\/\/movie.douban.com\/celebrity\/1315185\/",
			"avatars": {
				"small": "https://img3.doubanio.com\/img\/celebrity\/small\/1489830011.15.jpg",
				"large": "https://img3.doubanio.com\/img\/celebrity\/large\/1489830011.15.jpg",
				"medium": "https://img3.doubanio.com\/img\/celebrity\/medium\/1489830011.15.jpg"
			},
			"name": "\u738b\u5578\u5764",
			"id": "1315185"
		}],
		"year": "2017",
		"images": {
			"small": "https://img3.doubanio.com\/view\/movie_poster_cover\/ipst\/public\/p2450444730.webp",
			"large": "https://img3.doubanio.com\/view\/movie_poster_cover\/lpst\/public\/p2450444730.webp",
			"medium": "https://img3.doubanio.com\/view\/movie_poster_cover\/spst\/public\/p2450444730.webp"
		},
		"alt": "https:\/\/movie.douban.com\/subject\/26828019\/",
		"id": "26828019"
	}, {
		"rating": {
			"max": 10,
			"average": 6.4,
			"stars": "35",
			"min": 0
		},
		"genres": ["\u5267\u60c5", "\u8fd0\u52a8"],
		"title": "\u70b9\u4e94\u6b65",
		"casts": [{
			"alt": "https:\/\/movie.douban.com\/celebrity\/1316133\/",
			"avatars": {
				"small": "https://img3.doubanio.com\/img\/celebrity\/small\/35235.jpg",
				"large": "https://img3.doubanio.com\/img\/celebrity\/large\/35235.jpg",
				"medium": "https://img3.doubanio.com\/img\/celebrity\/medium\/35235.jpg"
			},
			"name": "\u6797\u8000\u58f0",
			"id": "1316133"
		}, {
			"alt": "https:\/\/movie.douban.com\/celebrity\/1362877\/",
			"avatars": {
				"small": "https://img1.doubanio.com\/img\/celebrity\/small\/1486453371.07.jpg",
				"large": "https://img1.doubanio.com\/img\/celebrity\/large\/1486453371.07.jpg",
				"medium": "https://img1.doubanio.com\/img\/celebrity\/medium\/1486453371.07.jpg"
			},
			"name": "\u80e1\u5b50\u5f64",
			"id": "1362877"
		}, {
			"alt": "https:\/\/movie.douban.com\/celebrity\/1274268\/",
			"avatars": {
				"small": "https://img1.doubanio.com\/img\/celebrity\/small\/1358427208.9.jpg",
				"large": "https://img1.doubanio.com\/img\/celebrity\/large\/1358427208.9.jpg",
				"medium": "https://img1.doubanio.com\/img\/celebrity\/medium\/1358427208.9.jpg"
			},
			"name": "\u5ed6\u542f\u667a",
			"id": "1274268"
		}],
		"collect_count": 1397,
		"original_title": "\u9ede\u4e94\u6b65",
		"subtype": "movie",
		"directors": [{
			"alt": "https:\/\/movie.douban.com\/celebrity\/1368141\/",
			"avatars": {
				"small": "https://img3.doubanio.com\/img\/celebrity\/small\/1486453167.84.jpg",
				"large": "https://img3.doubanio.com\/img\/celebrity\/large\/1486453167.84.jpg",
				"medium": "https://img3.doubanio.com\/img\/celebrity\/medium\/1486453167.84.jpg"
			},
			"name": "\u9648\u5fd7\u53d1",
			"id": "1368141"
		}],
		"year": "2016",
		"images": {
			"small": "https://img1.doubanio.com\/view\/movie_poster_cover\/ipst\/public\/p2454010849.webp",
			"large": "https://img1.doubanio.com\/view\/movie_poster_cover\/lpst\/public\/p2454010849.webp",
			"medium": "https://img1.doubanio.com\/view\/movie_poster_cover\/spst\/public\/p2454010849.webp"
		},
		"alt": "https:\/\/movie.douban.com\/subject\/26704592\/",
		"id": "26704592"
	}, {
		"rating": {
			"max": 10,
			"average": 8.2,
			"stars": "45",
			"min": 0
		},
		"genres": ["\u559c\u5267", "\u52a8\u753b", "\u6b4c\u821e"],
		"title": "\u6b22\u4e50\u597d\u58f0\u97f3",
		"casts": [{
			"alt": "https:\/\/movie.douban.com\/celebrity\/1040511\/",
			"avatars": {
				"small": "https://img3.doubanio.com\/img\/celebrity\/small\/1392653727.04.jpg",
				"large": "https://img3.doubanio.com\/img\/celebrity\/large\/1392653727.04.jpg",
				"medium": "https://img3.doubanio.com\/img\/celebrity\/medium\/1392653727.04.jpg"
			},
			"name": "\u9a6c\u4fee\u00b7\u9ea6\u5eb7\u7eb3",
			"id": "1040511"
		}, {
			"alt": "https:\/\/movie.douban.com\/celebrity\/1031217\/",
			"avatars": {
				"small": "https://img1.doubanio.com\/img\/celebrity\/small\/49827.jpg",
				"large": "https://img1.doubanio.com\/img\/celebrity\/large\/49827.jpg",
				"medium": "https://img1.doubanio.com\/img\/celebrity\/medium\/49827.jpg"
			},
			"name": "\u745e\u831c\u00b7\u5a01\u745f\u65af\u5f6d",
			"id": "1031217"
		}, {
			"alt": "https:\/\/movie.douban.com\/celebrity\/1041123\/",
			"avatars": {
				"small": "https://img3.doubanio.com\/img\/celebrity\/small\/1354381657.24.jpg",
				"large": "https://img3.doubanio.com\/img\/celebrity\/large\/1354381657.24.jpg",
				"medium": "https://img3.doubanio.com\/img\/celebrity\/medium\/1354381657.24.jpg"
			},
			"name": "\u585e\u601d\u00b7\u9ea6\u514b\u6cd5\u5170",
			"id": "1041123"
		}],
		"collect_count": 91452,
		"original_title": "Sing",
		"subtype": "movie",
		"directors": [{
			"alt": "https:\/\/movie.douban.com\/celebrity\/1303814\/",
			"avatars": {
				"small": "https://img1.doubanio.com\/img\/celebrity\/small\/21808.jpg",
				"large": "https://img1.doubanio.com\/img\/celebrity\/large\/21808.jpg",
				"medium": "https://img1.doubanio.com\/img\/celebrity\/medium\/21808.jpg"
			},
			"name": "\u52a0\u65af\u00b7\u8a79\u5b81\u65af",
			"id": "1303814"
		}, {
			"alt": "https:\/\/movie.douban.com\/celebrity\/1366253\/",
			"avatars": {
				"small": "https://img1.doubanio.com\/f\/movie\/ca527386eb8c4e325611e22dfcb04cc116d6b423\/pics\/movie\/celebrity-default-small.png",
				"large": "https://img3.doubanio.com\/f\/movie\/63acc16ca6309ef191f0378faf793d1096a3e606\/pics\/movie\/celebrity-default-large.png",
				"medium": "https://img1.doubanio.com\/f\/movie\/8dd0c794499fe925ae2ae89ee30cd225750457b4\/pics\/movie\/celebrity-default-medium.png"
			},
			"name": "\u514b\u91cc\u65af\u6258\u592b\u00b7\u5362\u5c14\u5fb7\u83b1",
			"id": "1366253"
		}],
		"year": "2016",
		"images": {
			"small": "https://img5.doubanio.com\/view\/movie_poster_cover\/ipst\/public\/p2411622136.webp",
			"large": "https://img5.doubanio.com\/view\/movie_poster_cover\/lpst\/public\/p2411622136.webp",
			"medium": "https://img5.doubanio.com\/view\/movie_poster_cover\/spst\/public\/p2411622136.webp"
		},
		"alt": "https:\/\/movie.douban.com\/subject\/26354572\/",
		"id": "26354572"
	}, {
		"rating": {
			"max": 10,
			"average": 8.4,
			"stars": "45",
			"min": 0
		},
		"genres": ["\u559c\u5267", "\u52a8\u753b"],
		"title": "\u9ea6\u515c\u00b7\u5f53\u5f53\u4f34\u6211\u5fc3",
		"casts": [{
			"alt": "https:\/\/movie.douban.com\/celebrity\/1050076\/",
			"avatars": {
				"small": "https://img3.doubanio.com\/img\/celebrity\/small\/34830.jpg",
				"large": "https://img3.doubanio.com\/img\/celebrity\/large\/34830.jpg",
				"medium": "https://img3.doubanio.com\/img\/celebrity\/medium\/34830.jpg"
			},
			"name": "\u9ec4\u79cb\u751f",
			"id": "1050076"
		}, {
			"alt": "https:\/\/movie.douban.com\/celebrity\/1127819\/",
			"avatars": {
				"small": "https://img3.doubanio.com\/img\/celebrity\/small\/1354430265.42.jpg",
				"large": "https://img3.doubanio.com\/img\/celebrity\/large\/1354430265.42.jpg",
				"medium": "https://img3.doubanio.com\/img\/celebrity\/medium\/1354430265.42.jpg"
			},
			"name": "\u5434\u541b\u5982",
			"id": "1127819"
		}, {
			"alt": "https:\/\/movie.douban.com\/celebrity\/1274477\/",
			"avatars": {
				"small": "https://img3.doubanio.com\/img\/celebrity\/small\/1468487353.74.jpg",
				"large": "https://img3.doubanio.com\/img\/celebrity\/large\/1468487353.74.jpg",
				"medium": "https://img3.doubanio.com\/img\/celebrity\/medium\/1468487353.74.jpg"
			},
			"name": "\u80e1\u6b4c",
			"id": "1274477"
		}],
		"collect_count": 91189,
		"original_title": "\u9ea5\u515c\u2027\u5679\u5679\u4f34\u6211\u5fc3",
		"subtype": "movie",
		"directors": [{
			"alt": "https:\/\/movie.douban.com\/celebrity\/1304710\/",
			"avatars": {
				"small": "https://img3.doubanio.com\/img\/celebrity\/small\/35544.jpg",
				"large": "https://img3.doubanio.com\/img\/celebrity\/large\/35544.jpg",
				"medium": "https://img3.doubanio.com\/img\/celebrity\/medium\/35544.jpg"
			},
			"name": "\u8c22\u7acb\u6587",
			"id": "1304710"
		}],
		"year": "2012",
		"images": {
			"small": "https://img3.doubanio.com\/view\/movie_poster_cover\/ipst\/public\/p2454027095.webp",
			"large": "https://img3.doubanio.com\/view\/movie_poster_cover\/lpst\/public\/p2454027095.webp",
			"medium": "https://img3.doubanio.com\/view\/movie_poster_cover\/spst\/public\/p2454027095.webp"
		},
		"alt": "https:\/\/movie.douban.com\/subject\/10772258\/",
		"id": "10772258"
	}, {
		"rating": {
			"max": 10,
			"average": 8.8,
			"stars": "45",
			"min": 0
		},
		"genres": ["\u52a8\u753b"],
		"title": "\u653b\u58f3\u673a\u52a8\u961fSSS 3D",
		"casts": [{
			"alt": null,
			"avatars": null,
			"name": "\u7530\u4e2d\u6566\u5b50",
			"id": null
		}, {
			"alt": null,
			"avatars": null,
			"name": "\u962a\u8129",
			"id": null
		}, {
			"alt": null,
			"avatars": null,
			"name": "\u5927\u585a\u660e\u592b",
			"id": null
		}],
		"collect_count": 2287,
		"original_title": "\u653b\u6bbb\u6a5f\u52d5\u968a STAND ALONE COMPLEX Solid State Society 3D",
		"subtype": "movie",
		"directors": [{
			"alt": null,
			"avatars": null,
			"name": "\u795e\u5c71\u5065\u6cbb",
			"id": null
		}],
		"year": "2011",
		"images": {
			"small": "https://img3.doubanio.com\/view\/movie_poster_cover\/ipst\/public\/p910801233.webp",
			"large": "https://img3.doubanio.com\/view\/movie_poster_cover\/lpst\/public\/p910801233.webp",
			"medium": "https://img3.doubanio.com\/view\/movie_poster_cover\/spst\/public\/p910801233.webp"
		},
		"alt": "https:\/\/movie.douban.com\/subject\/5403926\/",
		"id": "5403926"
	}, {
		"rating": {
			"max": 10,
			"average": 0,
			"stars": "00",
			"min": 0
		},
		"genres": ["\u6050\u6016"],
		"title": "\u60ca\u609a\u5c0f\u8bf4",
		"casts": [{
			"alt": "https:\/\/movie.douban.com\/celebrity\/1274390\/",
			"avatars": {
				"small": "https://img1.doubanio.com\/img\/celebrity\/small\/33149.jpg",
				"large": "https://img1.doubanio.com\/img\/celebrity\/large\/33149.jpg",
				"medium": "https://img1.doubanio.com\/img\/celebrity\/medium\/33149.jpg"
			},
			"name": "\u5415\u807f\u6765",
			"id": "1274390"
		}],
		"collect_count": 48,
		"original_title": "\u60ca\u609a\u5c0f\u8bf4",
		"subtype": "movie",
		"directors": [{
			"alt": "https:\/\/movie.douban.com\/celebrity\/1371541\/",
			"avatars": {
				"small": "https://img1.doubanio.com\/f\/movie\/ca527386eb8c4e325611e22dfcb04cc116d6b423\/pics\/movie\/celebrity-default-small.png",
				"large": "https://img3.doubanio.com\/f\/movie\/63acc16ca6309ef191f0378faf793d1096a3e606\/pics\/movie\/celebrity-default-large.png",
				"medium": "https://img1.doubanio.com\/f\/movie\/8dd0c794499fe925ae2ae89ee30cd225750457b4\/pics\/movie\/celebrity-default-medium.png"
			},
			"name": "\u767d\u4e3d\u4e3d",
			"id": "1371541"
		}],
		"year": "2015",
		"images": {
			"small": "https://img3.doubanio.com\/view\/movie_poster_cover\/ipst\/public\/p2450356235.webp",
			"large": "https://img3.doubanio.com\/view\/movie_poster_cover\/lpst\/public\/p2450356235.webp",
			"medium": "https://img3.doubanio.com\/view\/movie_poster_cover\/spst\/public\/p2450356235.webp"
		},
		"alt": "https:\/\/movie.douban.com\/subject\/26902792\/",
		"id": "26902792"
	}, {
		"rating": {
			"max": 10,
			"average": 8.3,
			"stars": "45",
			"min": 0
		},
		"genres": ["\u5267\u60c5", "\u52a8\u4f5c", "\u79d1\u5e7b"],
		"title": "\u91d1\u521a\u72fc3\uff1a\u6b8a\u6b7b\u4e00\u6218",
		"casts": [{
			"alt": "https:\/\/movie.douban.com\/celebrity\/1010508\/",
			"avatars": {
				"small": "https://img5.doubanio.com\/img\/celebrity\/small\/22036.jpg",
				"large": "https://img5.doubanio.com\/img\/celebrity\/large\/22036.jpg",
				"medium": "https://img5.doubanio.com\/img\/celebrity\/medium\/22036.jpg"
			},
			"name": "\u4f11\u00b7\u6770\u514b\u66fc",
			"id": "1010508"
		}, {
			"alt": "https:\/\/movie.douban.com\/celebrity\/1010540\/",
			"avatars": {
				"small": "https://img3.doubanio.com\/img\/celebrity\/small\/50451.jpg",
				"large": "https://img3.doubanio.com\/img\/celebrity\/large\/50451.jpg",
				"medium": "https://img3.doubanio.com\/img\/celebrity\/medium\/50451.jpg"
			},
			"name": "\u5e15\u7279\u91cc\u514b\u00b7\u65af\u56fe\u5c14\u7279",
			"id": "1010540"
		}, {
			"alt": "https:\/\/movie.douban.com\/celebrity\/1363476\/",
			"avatars": {
				"small": "https://img3.doubanio.com\/img\/celebrity\/small\/1489059638.74.jpg",
				"large": "https://img3.doubanio.com\/img\/celebrity\/large\/1489059638.74.jpg",
				"medium": "https://img3.doubanio.com\/img\/celebrity\/medium\/1489059638.74.jpg"
			},
			"name": "\u8fbe\u8299\u59ae\u00b7\u57fa\u6069",
			"id": "1363476"
		}],
		"collect_count": 163037,
		"original_title": "Logan",
		"subtype": "movie",
		"directors": [{
			"alt": "https:\/\/movie.douban.com\/celebrity\/1036395\/",
			"avatars": {
				"small": "https://img3.doubanio.com\/img\/celebrity\/small\/11282.jpg",
				"large": "https://img3.doubanio.com\/img\/celebrity\/large\/11282.jpg",
				"medium": "https://img3.doubanio.com\/img\/celebrity\/medium\/11282.jpg"
			},
			"name": "\u8a79\u59c6\u65af\u00b7\u66fc\u9ad8\u5fb7",
			"id": "1036395"
		}],
		"year": "2017",
		"images": {
			"small": "https://img3.doubanio.com\/view\/movie_poster_cover\/ipst\/public\/p2431980130.webp",
			"large": "https://img3.doubanio.com\/view\/movie_poster_cover\/lpst\/public\/p2431980130.webp",
			"medium": "https://img3.doubanio.com\/view\/movie_poster_cover\/spst\/public\/p2431980130.webp"
		},
		"alt": "https:\/\/movie.douban.com\/subject\/25765735\/",
		"id": "25765735"
	}, {
		"rating": {
			"max": 10,
			"average": 7.3,
			"stars": "40",
			"min": 0
		},
		"genres": ["\u5267\u60c5"],
		"title": "\u516b\u6708",
		"casts": [{
			"alt": "https:\/\/movie.douban.com\/celebrity\/1359768\/",
			"avatars": {
				"small": "https://img1.doubanio.com\/img\/celebrity\/small\/1480255486.29.jpg",
				"large": "https://img1.doubanio.com\/img\/celebrity\/large\/1480255486.29.jpg",
				"medium": "https://img1.doubanio.com\/img\/celebrity\/medium\/1480255486.29.jpg"
			},
			"name": "\u5b54\u7ef4\u4e00",
			"id": "1359768"
		}, {
			"alt": "https:\/\/movie.douban.com\/celebrity\/1359769\/",
			"avatars": {
				"small": "https://img1.doubanio.com\/f\/movie\/ca527386eb8c4e325611e22dfcb04cc116d6b423\/pics\/movie\/celebrity-default-small.png",
				"large": "https://img3.doubanio.com\/f\/movie\/63acc16ca6309ef191f0378faf793d1096a3e606\/pics\/movie\/celebrity-default-large.png",
				"medium": "https://img1.doubanio.com\/f\/movie\/8dd0c794499fe925ae2ae89ee30cd225750457b4\/pics\/movie\/celebrity-default-medium.png"
			},
			"name": "\u5f20\u6668",
			"id": "1359769"
		}, {
			"alt": "https:\/\/movie.douban.com\/celebrity\/1359770\/",
			"avatars": {
				"small": "https://img1.doubanio.com\/f\/movie\/ca527386eb8c4e325611e22dfcb04cc116d6b423\/pics\/movie\/celebrity-default-small.png",
				"large": "https://img3.doubanio.com\/f\/movie\/63acc16ca6309ef191f0378faf793d1096a3e606\/pics\/movie\/celebrity-default-large.png",
				"medium": "https://img1.doubanio.com\/f\/movie\/8dd0c794499fe925ae2ae89ee30cd225750457b4\/pics\/movie\/celebrity-default-medium.png"
			},
			"name": "\u90ed\u71d5\u82b8",
			"id": "1359770"
		}],
		"collect_count": 13767,
		"original_title": "\u516b\u6708",
		"subtype": "movie",
		"directors": [{
			"alt": "https:\/\/movie.douban.com\/celebrity\/1359764\/",
			"avatars": {
				"small": "https://img1.doubanio.com\/img\/celebrity\/small\/1480165173.37.jpg",
				"large": "https://img1.doubanio.com\/img\/celebrity\/large\/1480165173.37.jpg",
				"medium": "https://img1.doubanio.com\/img\/celebrity\/medium\/1480165173.37.jpg"
			},
			"name": "\u5f20\u5927\u78ca",
			"id": "1359764"
		}],
		"year": "2016",
		"images": {
			"small": "https://img3.doubanio.com\/view\/movie_poster_cover\/ipst\/public\/p2448419180.webp",
			"large": "https://img3.doubanio.com\/view\/movie_poster_cover\/lpst\/public\/p2448419180.webp",
			"medium": "https://img3.doubanio.com\/view\/movie_poster_cover\/spst\/public\/p2448419180.webp"
		},
		"alt": "https:\/\/movie.douban.com\/subject\/26820836\/",
		"id": "26820836"
	}, {
		"rating": {
			"max": 10,
			"average": 7.4,
			"stars": "40",
			"min": 0
		},
		"genres": ["\u52a8\u753b", "\u559c\u5267"],
		"title": "\u9ea6\u515c\u54cd\u5f53\u5f53",
		"casts": [{
			"alt": "https:\/\/movie.douban.com\/celebrity\/1274242\/",
			"avatars": {
				"small": "https://img5.doubanio.com\/img\/celebrity\/small\/1656.jpg",
				"large": "https://img5.doubanio.com\/img\/celebrity\/large\/1656.jpg",
				"medium": "https://img5.doubanio.com\/img\/celebrity\/medium\/1656.jpg"
			},
			"name": "\u9ec4\u6e24",
			"id": "1274242"
		}, {
			"alt": "https:\/\/movie.douban.com\/celebrity\/1050076\/",
			"avatars": {
				"small": "https://img3.doubanio.com\/img\/celebrity\/small\/34830.jpg",
				"large": "https://img3.doubanio.com\/img\/celebrity\/large\/34830.jpg",
				"medium": "https://img3.doubanio.com\/img\/celebrity\/medium\/34830.jpg"
			},
			"name": "\u9ec4\u79cb\u751f",
			"id": "1050076"
		}, {
			"alt": "https:\/\/movie.douban.com\/celebrity\/1127819\/",
			"avatars": {
				"small": "https://img3.doubanio.com\/img\/celebrity\/small\/1354430265.42.jpg",
				"large": "https://img3.doubanio.com\/img\/celebrity\/large\/1354430265.42.jpg",
				"medium": "https://img3.doubanio.com\/img\/celebrity\/medium\/1354430265.42.jpg"
			},
			"name": "\u5434\u541b\u5982",
			"id": "1127819"
		}],
		"collect_count": 105215,
		"original_title": "\u9ea5\u515c\u97ff\u7576\u7576",
		"subtype": "movie",
		"directors": [{
			"alt": "https:\/\/movie.douban.com\/celebrity\/1304710\/",
			"avatars": {
				"small": "https://img3.doubanio.com\/img\/celebrity\/small\/35544.jpg",
				"large": "https://img3.doubanio.com\/img\/celebrity\/large\/35544.jpg",
				"medium": "https://img3.doubanio.com\/img\/celebrity\/medium\/35544.jpg"
			},
			"name": "\u8c22\u7acb\u6587",
			"id": "1304710"
		}],
		"year": "2009",
		"images": {
			"small": "https://img1.doubanio.com\/view\/movie_poster_cover\/ipst\/public\/p2431279389.webp",
			"large": "https://img1.doubanio.com\/view\/movie_poster_cover\/lpst\/public\/p2431279389.webp",
			"medium": "https://img1.doubanio.com\/view\/movie_poster_cover\/spst\/public\/p2431279389.webp"
		},
		"alt": "https:\/\/movie.douban.com\/subject\/2277018\/",
		"id": "2277018"
	}, {
		"rating": {
			"max": 10,
			"average": 0,
			"stars": "00",
			"min": 0
		},
		"genres": ["\u559c\u5267", "\u5192\u9669"],
		"title": "\u9e21\u98de\u72d7\u8df3",
		"casts": [{
			"alt": "https:\/\/movie.douban.com\/celebrity\/1318441\/",
			"avatars": {
				"small": "https://img3.doubanio.com\/img\/celebrity\/small\/42891.jpg",
				"large": "https://img3.doubanio.com\/img\/celebrity\/large\/42891.jpg",
				"medium": "https://img3.doubanio.com\/img\/celebrity\/medium\/42891.jpg"
			},
			"name": "\u72c4\u5a01",
			"id": "1318441"
		}, {
			"alt": "https:\/\/movie.douban.com\/celebrity\/1028360\/",
			"avatars": {
				"small": "https://img1.doubanio.com\/img\/celebrity\/small\/1257.jpg",
				"large": "https://img1.doubanio.com\/img\/celebrity\/large\/1257.jpg",
				"medium": "https://img1.doubanio.com\/img\/celebrity\/medium\/1257.jpg"
			},
			"name": "\u9648\u89c2\u6cf0",
			"id": "1028360"
		}, {
			"alt": "https:\/\/movie.douban.com\/celebrity\/1316723\/",
			"avatars": {
				"small": "https://img1.doubanio.com\/img\/celebrity\/small\/37318.jpg",
				"large": "https://img1.doubanio.com\/img\/celebrity\/large\/37318.jpg",
				"medium": "https://img1.doubanio.com\/img\/celebrity\/medium\/37318.jpg"
			},
			"name": "\u9c81\u82ac",
			"id": "1316723"
		}],
		"collect_count": 49,
		"original_title": "\u9e21\u98de\u72d7\u8df3",
		"subtype": "movie",
		"directors": [{
			"alt": "https:\/\/movie.douban.com\/celebrity\/1330809\/",
			"avatars": {
				"small": "https://img1.doubanio.com\/img\/celebrity\/small\/1489145967.79.jpg",
				"large": "https://img1.doubanio.com\/img\/celebrity\/large\/1489145967.79.jpg",
				"medium": "https://img1.doubanio.com\/img\/celebrity\/medium\/1489145967.79.jpg"
			},
			"name": "\u7f57\u68cb",
			"id": "1330809"
		}],
		"year": "2017",
		"images": {
			"small": "https://img3.doubanio.com\/view\/movie_poster_cover\/ipst\/public\/p2449825125.webp",
			"large": "https://img3.doubanio.com\/view\/movie_poster_cover\/lpst\/public\/p2449825125.webp",
			"medium": "https://img3.doubanio.com\/view\/movie_poster_cover\/spst\/public\/p2449825125.webp"
		},
		"alt": "https:\/\/movie.douban.com\/subject\/26991765\/",
		"id": "26991765"
	}, {
		"rating": {
			"max": 10,
			"average": 0,
			"stars": "00",
			"min": 0
		},
		"genres": ["\u559c\u5267"],
		"title": "\u516d\u6708\u4e0e\u5f13\u7bad",
		"casts": [{
			"alt": "https:\/\/movie.douban.com\/celebrity\/1350321\/",
			"avatars": {
				"small": "https://img1.doubanio.com\/img\/celebrity\/small\/1463828122.98.jpg",
				"large": "https://img1.doubanio.com\/img\/celebrity\/large\/1463828122.98.jpg",
				"medium": "https://img1.doubanio.com\/img\/celebrity\/medium\/1463828122.98.jpg"
			},
			"name": "\u738b\u827a\u5609",
			"id": "1350321"
		}, {
			"alt": "https:\/\/movie.douban.com\/celebrity\/1327670\/",
			"avatars": {
				"small": "https://img1.doubanio.com\/img\/celebrity\/small\/1417833611.69.jpg",
				"large": "https://img1.doubanio.com\/img\/celebrity\/large\/1417833611.69.jpg",
				"medium": "https://img1.doubanio.com\/img\/celebrity\/medium\/1417833611.69.jpg"
			},
			"name": "\u6768\u6893\u94ce",
			"id": "1327670"
		}, {
			"alt": "https:\/\/movie.douban.com\/celebrity\/1317188\/",
			"avatars": {
				"small": "https://img5.doubanio.com\/img\/celebrity\/small\/1484623663.36.jpg",
				"large": "https://img5.doubanio.com\/img\/celebrity\/large\/1484623663.36.jpg",
				"medium": "https://img5.doubanio.com\/img\/celebrity\/medium\/1484623663.36.jpg"
			},
			"name": "\u675c\u7389\u660e",
			"id": "1317188"
		}],
		"collect_count": 30,
		"original_title": "\u516d\u6708\u4e0e\u5f13\u7bad",
		"subtype": "movie",
		"directors": [{
			"alt": "https:\/\/movie.douban.com\/celebrity\/1371537\/",
			"avatars": {
				"small": "https://img1.doubanio.com\/f\/movie\/ca527386eb8c4e325611e22dfcb04cc116d6b423\/pics\/movie\/celebrity-default-small.png",
				"large": "https://img3.doubanio.com\/f\/movie\/63acc16ca6309ef191f0378faf793d1096a3e606\/pics\/movie\/celebrity-default-large.png",
				"medium": "https://img1.doubanio.com\/f\/movie\/8dd0c794499fe925ae2ae89ee30cd225750457b4\/pics\/movie\/celebrity-default-medium.png"
			},
			"name": "\u6797\u6ce2",
			"id": "1371537"
		}],
		"year": "2017",
		"images": {
			"small": "https://img1.doubanio.com\/view\/movie_poster_cover\/ipst\/public\/p2446656269.webp",
			"large": "https://img1.doubanio.com\/view\/movie_poster_cover\/lpst\/public\/p2446656269.webp",
			"medium": "https://img1.doubanio.com\/view\/movie_poster_cover\/spst\/public\/p2446656269.webp"
		},
		"alt": "https:\/\/movie.douban.com\/subject\/26996771\/",
		"id": "26996771"
	}],
	"title": "\u6b63\u5728\u4e0a\u6620\u7684\u7535\u5f71-\u5317\u4eac"
}